src_perf/validity_reg/test.v
module test
(
    input validity_reg,
    output reg reset,
    output reg clk,
    output reg[2:0] input0, 
    output reg[2:0 ]input1
); 


initial begin
    $dumpfile("validity_reg.vcd");
	$dumpvars;

    @(posedge clk);
	@(posedge clk);
    @(posedge clk);
        input0 <= 1; 
        input1 <= 1;
    repeat(2) @(posedge clk);
        input0 <= 5; 
        input1 <= 1;
    repeat(2) @(posedge clk);
        input0 <= 0; 
        input1 <= 8;
    repeat(2) @(posedge clk);
        input0 <= 67; 
        input1 <= 67;
    repeat(27) @(posedge clk);
        input0 <= 1; 
        input1 <= 1;
    $finish;
end

//clk.
initial clk <= 0;
always	#2 clk <= ~clk;

//resetn.
initial
begin
	#0
	reset = 1'b0;
	@(posedge clk);
	reset = 1'b0;
	@(posedge clk);
	reset = 1'b1;
end

endmodule

src_perf/perf_sys/validity_reg.v

`ifndef validity_reg
`define validity_reg

module validity_reg(
    input clk,
    input reset,
    input[2:0] input0,
    input[2:0] input1,

    output reg validity_reg
);

    always @ (posedge clk) begin
        if(reset) begin
            if(input0 == 1 && input1 == 1) begin
                validity_reg <= 1;
            end else begin
                validity_reg <= 0;
            end
        end else begin
            validity_reg <= 0;
        end
    end

endmodule

`endif

src_perf/validity_reg/test_bench.v
`timescale 1ns/100ps

`include "validity_reg.v"
`include "test.v"

module test_bench;

wire clk, reset, validity_reg;
wire[2:0] input0, input1;

validity_reg COND(
    /*AUTOINST*/
		  // Outputs
		  .validity_reg		(validity_reg),
		  // Inputs
		  .clk			(clk),
		  .reset		(reset),
		  .input0		(input0[2:0]),
		  .input1		(input1[2:0]));

test TEST(
    /*AUTOINST*/
	  // Outputs
	  .reset			(reset),
	  .clk				(clk),
	  .input0			(input0[2:0]),
	  .input1			(input1[2:0]),
	  // Inputs
	  .validity_reg			(validity_reg));
endmodule

src_perf/validity_reg/validity_reg.vcd
$date
	Sun Jul 11 23:42:10 2021
$end
$version
	Icarus Verilog
$end
$timescale
	100ps
$end
$scope module test_bench $end
$var wire 1 ! validity_reg $end
$var wire 1 " reset $end
$var wire 3 # input1 [2:0] $end
$var wire 3 $ input0 [2:0] $end
$var wire 1 % clk $end
$scope module COND $end
$var wire 1 " reset $end
$var wire 3 & input1 [2:0] $end
$var wire 3 ' input0 [2:0] $end
$var wire 1 % clk $end
$var reg 1 ! validity_reg $end
$upscope $end
$scope module TEST $end
$var wire 1 ! validity_reg $end
$var reg 1 % clk $end
$var reg 3 ( input0 [2:0] $end
$var reg 3 ) input1 [2:0] $end
$var reg 1 " reset $end
$upscope $end
$upscope $end
$enddefinitions $end
#0
$dumpvars
bx )
bx (
bx '
bx &
0%
bx $
bx #
0"
x!
$end
#20
0!
1%
#40
0%
#60
1"
1%
#80
0%
#100
b1 #
b1 &
b1 )
b1 $
b1 '
b1 (
1%
#120
0%
#140
1!
1%
#160
0%
#180
b101 $
b101 '
b101 (
1%
#200
0%
#220
0!
1%
#240
0%
#260
b0 #
b0 &
b0 )
b0 $
b0 '
b0 (
1%
#280
0%
#300
1!
1%
#320
0%
#340
b11 #
b11 &
b11 )
b11 $
b11 '
b11 (
1%
